openbuffet_toolkit/__init__.py
openbuffet_toolkit/tool_config/__init__.py
openbuffet_toolkit/tool_config/env_handler.py
openbuffet_toolkit/tool_hface/__init__.py
openbuffet_toolkit/tool_hface/hface_handler.py
openbuffet_toolkit/tool_logger/__init__.py
openbuffet_toolkit/tool_logger/logger_handler.py
openbuffet_toolkit/tool_profiler/__init__.py
openbuffet_toolkit/tool_profiler/profiler_handler.py
openbuffet_toolkit-1.3.6.dist-info/licenses/AUTHORS.rst
openbuffet_toolkit-1.3.6.dist-info/licenses/LICENSE
openbuffet_toolkit-1.3.6.dist-info/METADATA
openbuffet_toolkit-1.3.6.dist-info/WHEEL
openbuffet_toolkit-1.3.6.dist-info/top_level.txt
openbuffet_toolkit-1.3.6.dist-info/RECORD
