Metadata-Version: 2.4
Name: openbuffet_toolkit
Version: 1.3.6
Summary: general purpose python toolkit
Author-email: ferdi kurnaz <ferdikurnazdm@gmail.com>
Maintainer-email: ferdi kurnaz <ferdikurnazdm@gmail.com>
License: MIT license
Project-URL: bugs, https://github.com/ferdikurnazdm/openbuffet_toolkit/issues
Project-URL: changelog, https://github.com/ferdikurnazdm/openbuffet_toolkit/blob/master/changelog.md
Project-URL: homepage, https://github.com/ferdikurnazdm/openbuffet_toolkit
License-File: LICENSE
License-File: AUTHORS.rst
Provides-Extra: dev
Requires-Dist: coverage; extra == "dev"
Requires-Dist: mypy; extra == "dev"
Requires-Dist: pytest; extra == "dev"
Requires-Dist: ruff; extra == "dev"
Dynamic: license-file
